server.py
mseep_aws_cost_explorer_mcp-0.1.1.dist-info/licenses/LICENSE
mseep_aws_cost_explorer_mcp-0.1.1.dist-info/METADATA
mseep_aws_cost_explorer_mcp-0.1.1.dist-info/WHEEL
mseep_aws_cost_explorer_mcp-0.1.1.dist-info/entry_points.txt
mseep_aws_cost_explorer_mcp-0.1.1.dist-info/top_level.txt
mseep_aws_cost_explorer_mcp-0.1.1.dist-info/RECORD
