Metadata-Version: 2.4
Name: mseep-aws-cost-explorer-mcp
Version: 0.1.1
Summary: Add your description here
Author-email: mseep <support@skydeck.ai>
Requires-Python: <3.13,>=3.12
License-File: LICENSE
Requires-Dist: boto3>=1.37.9
Requires-Dist: botocore>=1.37.9
Requires-Dist: chainlit>=2.4.1
Requires-Dist: jmespath>=1.0.1
Requires-Dist: langchain>=0.3.20
Requires-Dist: langchain-anthropic>=0.3.9
Requires-Dist: langchain-aws>=0.2.15
Requires-Dist: langchain-mcp-adapters>=0.0.4
Requires-Dist: langgraph>=0.3.10
Requires-Dist: mcp>=1.3.0
Requires-Dist: pandas>=2.2.3
Requires-Dist: pydantic>=2.10.6
Requires-Dist: streamlit>=1.44.1
Requires-Dist: tabulate>=0.9.0
Requires-Dist: typing-extensions>=4.12.2
Dynamic: license-file
